nmapper/__init__.py
nmapper/__main__.py
nmapper/nmapper.py
nmapper/resources/settings.ini
nmapper-0.3.1.dist-info/LICENSE
nmapper-0.3.1.dist-info/METADATA
nmapper-0.3.1.dist-info/WHEEL
nmapper-0.3.1.dist-info/entry_points.txt
nmapper-0.3.1.dist-info/top_level.txt
nmapper-0.3.1.dist-info/RECORD
