Metadata-Version: 2.1
Name: nmapper
Version: 0.3.1
Summary: Scan and list local network hosts
Home-page: https://github.com/bandaangosta/nmapper
Author: Jose L. Ortiz
Author-email: jlortiz@uc.cl
License: MIT
Platform: UNKNOWN
Classifier: Programming Language :: Python :: 3
Classifier: License :: OSI Approved :: MIT License
Classifier: Operating System :: OS Independent
Requires-Dist: click (==7.1.2)
Requires-Dist: typer (==0.3.2)
Requires-Dist: configparser (==4.0.2)
Requires-Dist: python-nmap (==0.6.1)
Requires-Dist: config-path (==1.0.2)
Requires-Dist: rich (==10.9.0)
